{"411238906378584066":{"cash":2,"wheatcrops":0,"corncrops":0,"potatocrops":0,"sugarcanecrops":0,"carrotcrops":0,"wheat":0,"corn":0,"potato":0,"sugarcane":0,"carrot":0,"redipanda.user.afk":0,"redipanda.user.afk.notice":0},"723513777521295480":{"cash":7,"wheatcrops":0,"corncrops":0,"potatocrops":0,"sugarcanecrops":0,"carrotcrops":0,"wheat":0,"corn":0,"potato":0,"sugarcane":0,"carrot":0,"redipanda.user.afk":0,"redipanda.user.afk.notice":0},"379327265131200533":{"cash":1,"wheatcrops":0,"corncrops":0,"potatocrops":0,"sugarcanecrops":0,"carrotcrops":0,"wheat":0,"corn":0,"potato":0,"sugarcane":0,"carrot":0,"redipanda.user.afk":0,"redipanda.user.afk.notice":0},"280815998402166784":{"cash":2,"wheatcrops":0,"corncrops":0,"potatocrops":0,"sugarcanecrops":0,"carrotcrops":0,"wheat":0,"corn":0,"potato":0,"sugarcane":0,"carrot":0,"redipanda.user.afk":0,"redipanda.user.afk.notice":0},"588061170607456317":{"cash":19,"wheatcrops":0,"corncrops":0,"potatocrops":0,"sugarcanecrops":0,"carrotcrops":0,"wheat":0,"corn":0,"potato":0,"sugarcane":0,"carrot":0,"redipanda.user.afk":0,"redipanda.user.afk.notice":0},"593161918563352608":{"cash":20,"wheatcrops":0,"corncrops":0,"potatocrops":0,"sugarcanecrops":0,"carrotcrops":0,"wheat":0,"corn":0,"potato":0,"sugarcane":0,"carrot":0,"redipanda.user.afk":0,"redipanda.user.afk.notice":0},"334361254435225602":{"cash":7},"444511381627076611":{"cash":1},"344430002344820737":{"cash":3,"wheatcrops":0,"corncrops":0,"potatocrops":0,"sugarcanecrops":0,"carrotcrops":0,"wheat":0,"corn":0,"potato":0,"sugarcane":0,"carrot":0,"redipanda.user.afk":0,"redipanda.user.afk.notice":0},"646044526741291008":{"cash":10},"318705525049131008":{"cash":2,"wheatcrops":0,"corncrops":0,"potatocrops":0,"sugarcanecrops":0,"carrotcrops":0,"wheat":0,"corn":0,"potato":0,"sugarcane":0,"carrot":0,"redipanda.user.afk":0,"redipanda.user.afk.notice":0},"520419419927609345":{"cash":5000197,"wheatcrops":0,"corncrops":0,"potatocrops":0,"sugarcanecrops":0,"carrotcrops":0,"wheat":0,"corn":0,"potato":0,"sugarcane":0,"carrot":0,"redipanda.user.afk":0,"redipanda.user.afk.notice":0,"bank":0,"total-slot":0,"slot-win":0},"386597444080893953":{"cash":16,"wheatcrops":0,"corncrops":0,"potatocrops":0,"sugarcanecrops":0,"carrotcrops":0,"wheat":0,"corn":0,"potato":0,"sugarcane":0,"carrot":0,"redipanda.user.afk":0,"redipanda.user.afk.notice":0},"752212890328498176":{"cash":3,"wheatcrops":0,"corncrops":0,"potatocrops":0,"sugarcanecrops":0,"carrotcrops":0,"wheat":0,"corn":0,"potato":0,"sugarcane":0,"carrot":0,"redipanda.user.afk":0,"redipanda.user.afk.notice":0},"798615228728082462":{"cash":2,"wheatcrops":0,"corncrops":0,"potatocrops":0,"sugarcanecrops":0,"carrotcrops":0,"wheat":0,"corn":0,"potato":0,"sugarcane":0,"carrot":0,"redipanda.user.afk":0,"redipanda.user.afk.notice":0},"754078160416669786":{"cash":1,"wheatcrops":0,"corncrops":0,"potatocrops":0,"sugarcanecrops":0,"carrotcrops":0,"wheat":0,"corn":0,"potato":0,"sugarcane":0,"carrot":0,"redipanda.user.afk":0,"redipanda.user.afk.notice":0},"423203831971708958":{"cash":2,"wheatcrops":0,"corncrops":0,"potatocrops":0,"sugarcanecrops":0,"carrotcrops":0,"wheat":0,"corn":0,"potato":0,"sugarcane":0,"carrot":0,"redipanda.user.afk":0,"redipanda.user.afk.notice":0},"420480067374809094":{"cash":1,"wheatcrops":0,"corncrops":0,"potatocrops":0,"sugarcanecrops":0,"carrotcrops":0,"wheat":0,"corn":0,"potato":0,"sugarcane":0,"carrot":0,"redipanda.user.afk":0,"redipanda.user.afk.notice":0},"333665491367493635":{"cash":3,"wheatcrops":0,"corncrops":0,"potatocrops":0,"sugarcanecrops":0,"carrotcrops":0,"wheat":0,"corn":0,"potato":0,"sugarcane":0,"carrot":0,"redipanda.user.afk":0,"redipanda.user.afk.notice":0}}